sopel_cryptocurrency/__init__.py
sopel_cryptocurrency/cryptocurrency.py
sopel_cryptocurrency-2.0.0.dist-info/licenses/LICENSE
sopel_cryptocurrency-2.0.0.dist-info/METADATA
sopel_cryptocurrency-2.0.0.dist-info/WHEEL
sopel_cryptocurrency-2.0.0.dist-info/entry_points.txt
sopel_cryptocurrency-2.0.0.dist-info/top_level.txt
sopel_cryptocurrency-2.0.0.dist-info/RECORD
