Metadata-Version: 2.4
Name: sopel-cryptocurrency
Version: 2.0.0
Summary: A Sopel IRC bot plugin for cryptocurrency price lookups
Author-email: Rusty Bower <rusty@rustybower.com>
Maintainer-email: Rusty Bower <rusty@rustybower.com>
License-Expression: MIT
Project-URL: Homepage, https://github.com/RustyBower/sopel-cryptocurrency
Project-URL: Bug Tracker, https://github.com/RustyBower/sopel-cryptocurrency/issues
Keywords: sopel,plugin,bot,irc,cryptocurrency,bitcoin,ethereum
Platform: Linux x86, x86-64
Classifier: Development Status :: 5 - Production/Stable
Classifier: Intended Audience :: Developers
Classifier: Intended Audience :: System Administrators
Classifier: Operating System :: POSIX :: Linux
Classifier: Programming Language :: Python :: 3.8
Classifier: Programming Language :: Python :: 3.9
Classifier: Programming Language :: Python :: 3.10
Classifier: Programming Language :: Python :: 3.11
Classifier: Programming Language :: Python :: 3.12
Classifier: Topic :: Communications :: Chat :: Internet Relay Chat
Requires-Python: <4,>=3.8
License-File: LICENSE
Requires-Dist: arrow
Requires-Dist: requests
Requires-Dist: sopel>=8
Provides-Extra: dev
Requires-Dist: pytest; extra == "dev"
Requires-Dist: flake8; extra == "dev"
Dynamic: license-file
